convertkit
