Metadata-Version: 1.0
Name: convertkit
Version: 0.4
Summary: API Client for ConvertKit v3
Home-page: https://github.com/justinabrahms/python-convertkit/
Author: Justin Abrahms
Author-email: justin@abrah.ms
License: BSD
Platform: UNKNOWN
